{"title":"PHP 过滤特殊符号","slug":"php-filter-special-symbols","date":"2021-09-30T14:52:40.000Z","updated":"2021-09-30T15:01:02.954Z","comments":true,"path":"api/articles/php-filter-special-symbols.json","photos":[],"link":"","excerpt":null,"covers":null,"content":"<figure class=\"highlight php\"><table><tr><td class=\"gutter\"><pre><span class=\"line\">1</span><br><span class=\"line\">2</span><br><span class=\"line\">3</span><br><span class=\"line\">4</span><br><span class=\"line\">5</span><br><span class=\"line\">6</span><br><span class=\"line\">7</span><br><span class=\"line\">8</span><br></pre></td><td class=\"code\"><pre><span class=\"line\"><span class=\"comment\">// 过滤特殊字符，仅保留中文、字母、数字、下划线</span></span><br><span class=\"line\"><span class=\"function\"><span class=\"keyword\">function</span> <span class=\"title\">match_chinese</span>(<span class=\"params\"><span class=\"variable\">$chars</span>, <span class=\"variable\">$encoding</span> = <span class=\"string\">&#x27;utf8&#x27;</span></span>)</span></span><br><span class=\"line\"><span class=\"function\"></span>&#123;</span><br><span class=\"line\">    <span class=\"variable\">$pattern</span> = (<span class=\"variable\">$encoding</span> == <span class=\"string\">&#x27;utf8&#x27;</span>) ? <span class=\"string\">&#x27;/[\\x&#123;4e00&#125;-\\x&#123;9fa5&#125;a-zA-Z0-9_]/u&#x27;</span> : <span class=\"string\">&#x27;/[\\x80-\\xFF]/&#x27;</span>;</span><br><span class=\"line\">    preg_match_all(<span class=\"variable\">$pattern</span>, <span class=\"variable\">$chars</span>, <span class=\"variable\">$result</span>);</span><br><span class=\"line\">    <span class=\"variable\">$temp</span> = join(<span class=\"string\">&#x27;&#x27;</span>, <span class=\"variable\">$result</span>[<span class=\"number\">0</span>]);</span><br><span class=\"line\">    <span class=\"keyword\">return</span> <span class=\"variable\">$temp</span>;</span><br><span class=\"line\">&#125;</span><br></pre></td></tr></table></figure>\n","categories":[],"tags":[]}